<products>
  <venue>
    <title>4-D Theater</title>
    <memberonly>0</memberonly>
    <capacity>98</capacity>
    <shows>
      <show>
        <title>Polar Express</title>
        <location>4-D Theater</location>
        <length>15</length>
        <eventnumber>1224</eventnumber>
        <date>
          <eventdate>2018/11/15</eventdate>
          <times>
            <time>
              <starttime schoolonly="0">10:20</starttime>
              <endtime schoolonly="0">10:35</endtime>
              <instock>96</instock>
            </time>
            <time>
              <starttime schoolonly="0">11:40</starttime>
              <endtime schoolonly="0">11:55</endtime>
              <instock>93</instock>
            </time>
            <time>
              <starttime schoolonly="0">12:20</starttime>
              <endtime schoolonly="0">12:35</endtime>
              <instock>95</instock>
            </time>
            <time>
              <starttime schoolonly="0">13:00</starttime>
              <endtime schoolonly="0">13:15</endtime>
              <instock>92</instock>
            </time>
            <time>
              <starttime schoolonly="0">13:40</starttime>
              <endtime schoolonly="0">13:55</endtime>
              <instock>94</instock>
            </time>
            <time>
              <starttime schoolonly="0">14:20</starttime>
              <endtime schoolonly="0">14:35</endtime>
              <instock>98</instock>
            </time>
            <time>
              <starttime schoolonly="0">15:40</starttime>
              <endtime schoolonly="0">15:55</endtime>
              <instock>93</instock>
            </time>
            <time>
              <starttime schoolonly="0">16:40</starttime>
              <endtime schoolonly="0">16:55</endtime>
              <instock>98</instock>
            </time>
          </times>
        </date>
      </show>
      <show>
        <title>Shark: A 4-D Experience</title>
        <location>4-D Theater</location>
        <length>15</length>
        <eventnumber>26047</eventnumber>
        <date>
          <eventdate>2018/11/15</eventdate>
          <times>
            <time>
              <starttime schoolonly="0">09:40</starttime>
              <endtime schoolonly="0">09:55</endtime>
              <instock>98</instock>
            </time>
            <time>
              <starttime schoolonly="0">10:40</starttime>
              <endtime schoolonly="0">10:55</endtime>
              <instock>98</instock>
            </time>
            <time>
              <starttime schoolonly="0">11:20</starttime>
              <endtime schoolonly="0">11:35</endtime>
              <instock>98</instock>
            </time>
            <time>
              <starttime schoolonly="0">12:40</starttime>
              <endtime schoolonly="0">12:55</endtime>
              <instock>89</instock>
            </time>
            <time>
              <starttime schoolonly="0">13:20</starttime>
              <endtime schoolonly="0">13:35</endtime>
              <instock>98</instock>
            </time>
            <time>
              <starttime schoolonly="0">14:40</starttime>
              <endtime schoolonly="0">14:55</endtime>
              <instock>91</instock>
            </time>
            <time>
              <starttime schoolonly="0">15:20</starttime>
              <endtime schoolonly="0">15:35</endtime>
              <instock>95</instock>
            </time>
            <time>
              <starttime schoolonly="0">16:00</starttime>
              <endtime schoolonly="0">16:15</endtime>
              <instock>96</instock>
            </time>
          </times>
        </date>
      </show>
      <show>
        <title>Splash and Bubbles</title>
        <location>4-D Theater</location>
        <length>15</length>
        <eventnumber>41870</eventnumber>
        <date>
          <eventdate>2018/11/15</eventdate>
          <times>
            <time>
              <starttime schoolonly="0">10:00</starttime>
              <endtime schoolonly="0">10:15</endtime>
              <instock>98</instock>
            </time>
            <time>
              <starttime schoolonly="0">11:00</starttime>
              <endtime schoolonly="0">11:15</endtime>
              <instock>98</instock>
            </time>
            <time>
              <starttime schoolonly="0">12:00</starttime>
              <endtime schoolonly="0">12:15</endtime>
              <instock>90</instock>
            </time>
            <time>
              <starttime schoolonly="0">14:00</starttime>
              <endtime schoolonly="0">14:15</endtime>
              <instock>98</instock>
            </time>
            <time>
              <starttime schoolonly="0">15:00</starttime>
              <endtime schoolonly="0">15:15</endtime>
              <instock>98</instock>
            </time>
            <time>
              <starttime schoolonly="0">16:20</starttime>
              <endtime schoolonly="0">16:35</endtime>
              <instock>98</instock>
            </time>
          </times>
        </date>
      </show>
    </shows>
  </venue>
  <venue>
    <title>Butterfly Garden</title>
    <memberonly>0</memberonly>
    <capacity>30</capacity>
    <shows>
      <show>
        <title>Butterfly Garden</title>
        <location>Butterfly Garden</location>
        <length>30</length>
        <eventnumber>158</eventnumber>
        <date>
          <eventdate>2018/11/15</eventdate>
          <times>
            <time>
              <starttime schoolonly="0">10:00</starttime>
              <endtime schoolonly="0">10:30</endtime>
              <instock>30</instock>
            </time>
            <time>
              <starttime schoolonly="0">10:15</starttime>
              <endtime schoolonly="0">10:45</endtime>
              <instock>28</instock>
            </time>
            <time>
              <starttime schoolonly="0">10:30</starttime>
              <endtime schoolonly="0">11:00</endtime>
              <instock>28</instock>
            </time>
            <time>
              <starttime schoolonly="0">10:45</starttime>
              <endtime schoolonly="0">11:15</endtime>
              <instock>30</instock>
            </time>
            <time>
              <starttime schoolonly="0">11:00</starttime>
              <endtime schoolonly="0">11:30</endtime>
              <instock>30</instock>
            </time>
            <time>
              <starttime schoolonly="0">11:15</starttime>
              <endtime schoolonly="0">11:45</endtime>
              <instock>29</instock>
            </time>
            <time>
              <starttime schoolonly="0">11:30</starttime>
              <endtime schoolonly="0">12:00</endtime>
              <instock>27</instock>
            </time>
            <time>
              <starttime schoolonly="0">11:45</starttime>
              <endtime schoolonly="0">12:15</endtime>
              <instock>30</instock>
            </time>
            <time>
              <starttime schoolonly="0">12:00</starttime>
              <endtime schoolonly="0">12:30</endtime>
              <instock>30</instock>
            </time>
            <time>
              <starttime schoolonly="0">12:15</starttime>
              <endtime schoolonly="0">12:45</endtime>
              <instock>30</instock>
            </time>
            <time>
              <starttime schoolonly="0">12:30</starttime>
              <endtime schoolonly="0">13:00</endtime>
              <instock>23</instock>
            </time>
            <time>
              <starttime schoolonly="0">12:45</starttime>
              <endtime schoolonly="0">13:15</endtime>
              <instock>30</instock>
            </time>
            <time>
              <starttime schoolonly="0">13:00</starttime>
              <endtime schoolonly="0">13:30</endtime>
              <instock>30</instock>
            </time>
            <time>
              <starttime schoolonly="0">13:15</starttime>
              <endtime schoolonly="0">13:45</endtime>
              <instock>26</instock>
            </time>
            <time>
              <starttime schoolonly="0">13:30</starttime>
              <endtime schoolonly="0">14:00</endtime>
              <instock>25</instock>
            </time>
            <time>
              <starttime schoolonly="0">13:45</starttime>
              <endtime schoolonly="0">14:15</endtime>
              <instock>30</instock>
            </time>
            <time>
              <starttime schoolonly="0">14:00</starttime>
              <endtime schoolonly="0">14:30</endtime>
              <instock>28</instock>
            </time>
            <time>
              <starttime schoolonly="0">14:15</starttime>
              <endtime schoolonly="0">14:45</endtime>
              <instock>28</instock>
            </time>
            <time>
              <starttime schoolonly="0">14:30</starttime>
              <endtime schoolonly="0">15:00</endtime>
              <instock>30</instock>
            </time>
            <time>
              <starttime schoolonly="0">14:45</starttime>
              <endtime schoolonly="0">15:15</endtime>
              <instock>28</instock>
            </time>
            <time>
              <starttime schoolonly="0">15:00</starttime>
              <endtime schoolonly="0">15:30</endtime>
              <instock>27</instock>
            </time>
            <time>
              <starttime schoolonly="0">15:15</starttime>
              <endtime schoolonly="0">15:45</endtime>
              <instock>30</instock>
            </time>
            <time>
              <starttime schoolonly="0">15:30</starttime>
              <endtime schoolonly="0">16:00</endtime>
              <instock>30</instock>
            </time>
            <time>
              <starttime schoolonly="0">15:45</starttime>
              <endtime schoolonly="0">16:15</endtime>
              <instock>30</instock>
            </time>
            <time>
              <starttime schoolonly="0">16:00</starttime>
              <endtime schoolonly="0">16:30</endtime>
              <instock>30</instock>
            </time>
            <time>
              <starttime schoolonly="0">16:15</starttime>
              <endtime schoolonly="0">16:45</endtime>
              <instock>30</instock>
            </time>
            <time>
              <starttime schoolonly="0">16:30</starttime>
              <endtime schoolonly="0">17:00</endtime>
              <instock>28</instock>
            </time>
          </times>
        </date>
      </show>
    </shows>
  </venue>
  <venue>
    <title>Charles Hayden Planetarium</title>
    <memberonly>0</memberonly>
    <capacity>209</capacity>
    <shows>
      <show>
        <title>Destination Mars: The New Frontier</title>
        <location>Planetarium</location>
        <length>35</length>
        <eventnumber>45692</eventnumber>
        <date>
          <eventdate>2018/11/15</eventdate>
          <times>
            <time>
              <starttime schoolonly="0">12:30</starttime>
              <endtime schoolonly="0">13:05</endtime>
              <instock>96</instock>
            </time>
            <time>
              <starttime schoolonly="0">15:30</starttime>
              <endtime schoolonly="0">16:05</endtime>
              <instock>200</instock>
            </time>
          </times>
        </date>
      </show>
      <show>
        <title>Explore the Galaxy</title>
        <location>Planetarium</location>
        <length>45</length>
        <eventnumber>1290</eventnumber>
        <date>
          <eventdate>2018/11/15</eventdate>
          <times>
            <time>
              <starttime schoolonly="1">11:30</starttime>
              <endtime schoolonly="1">12:15</endtime>
              <instock>144</instock>
            </time>
          </times>
        </date>
      </show>
      <show>
        <title>Magic Tree House: Space Mission</title>
        <location>Planetarium</location>
        <length>30</length>
        <eventnumber>1394</eventnumber>
        <date>
          <eventdate>2018/11/15</eventdate>
          <times>
            <time>
              <starttime schoolonly="0">13:30</starttime>
              <endtime schoolonly="0">14:00</endtime>
              <instock>141</instock>
            </time>
          </times>
        </date>
      </show>
      <show>
        <title>SCH: Explore the Solar System</title>
        <location>Planetarium</location>
        <length>45</length>
        <eventnumber>1291</eventnumber>
        <date>
          <eventdate>2018/11/15</eventdate>
          <times>
            <time>
              <starttime schoolonly="1">10:30</starttime>
              <endtime schoolonly="1">11:15</endtime>
              <instock>57</instock>
            </time>
          </times>
        </date>
      </show>
      <show>
        <title>Undiscovered Worlds: The Search Beyond Our Sun</title>
        <location>Planetarium</location>
        <length>35</length>
        <eventnumber>7319</eventnumber>
        <date>
          <eventdate>2018/11/15</eventdate>
          <times>
            <time>
              <starttime schoolonly="0">14:30</starttime>
              <endtime schoolonly="0">15:05</endtime>
              <instock>198</instock>
            </time>
          </times>
        </date>
      </show>
    </shows>
  </venue>
  <venue>
    <title>Drop-In Activities</title>
    <memberonly>0</memberonly>
    <capacity>30000</capacity>
    <shows>
      <show>
        <title>Design Challenges</title>
        <location>Engineering Design Workshop</location>
        <length>120</length>
        <eventnumber>6068</eventnumber>
        <date>
          <eventdate>2018/11/15</eventdate>
          <times>
            <time>
              <starttime schoolonly="0">10:00</starttime>
              <endtime schoolonly="0">12:00</endtime>
              <instock>30000</instock>
            </time>
          </times>
        </date>
      </show>
      <show>
        <title>Hands-On Laboratory</title>
        <location>Various</location>
        <length>120</length>
        <eventnumber>6071</eventnumber>
        <date>
          <eventdate>2018/11/15</eventdate>
          <times>
            <time>
              <starttime schoolonly="0">10:00</starttime>
              <endtime schoolonly="0">12:00</endtime>
              <instock>30000</instock>
            </time>
            <time>
              <starttime schoolonly="0">12:00</starttime>
              <endtime schoolonly="0">14:00</endtime>
              <instock>30000</instock>
            </time>
          </times>
        </date>
      </show>
    </shows>
  </venue>
  <venue>
    <title>Live Presentations</title>
    <memberonly>0</memberonly>
    <capacity>30000</capacity>
    <shows>
      <show>
        <title>Afternoon Report: From People to Prize: A Nobel Pursuit</title>
        <location>Gordon Current Science &amp; Technology Center</location>
        <length>20</length>
        <eventnumber>8143</eventnumber>
        <date>
          <eventdate>2018/11/15</eventdate>
          <times>
            <time>
              <starttime schoolonly="0">14:30</starttime>
              <endtime schoolonly="0">14:50</endtime>
              <instock>30000</instock>
            </time>
          </times>
        </date>
      </show>
      <show>
        <title>Lightning!</title>
        <location>Theater of Electricity</location>
        <length>20</length>
        <eventnumber>1399</eventnumber>
        <date>
          <eventdate>2018/11/15</eventdate>
          <times>
            <time>
              <starttime schoolonly="0">12:00</starttime>
              <endtime schoolonly="0">12:20</endtime>
              <instock>30000</instock>
            </time>
            <time>
              <starttime schoolonly="0">14:00</starttime>
              <endtime schoolonly="0">14:20</endtime>
              <instock>30000</instock>
            </time>
          </times>
        </date>
      </show>
      <show>
        <title>Live Animal</title>
        <location>Shapiro Family Science Live! Stage</location>
        <length>20</length>
        <eventnumber>8140</eventnumber>
        <date>
          <eventdate>2018/11/15</eventdate>
          <times>
            <time>
              <starttime schoolonly="0">10:30</starttime>
              <endtime schoolonly="0">10:50</endtime>
              <instock>30000</instock>
            </time>
            <time>
              <starttime schoolonly="0">13:30</starttime>
              <endtime schoolonly="0">13:50</endtime>
              <instock>30000</instock>
            </time>
          </times>
        </date>
      </show>
      <show>
        <title>Science Live!</title>
        <location>Shapiro Family Science Live! Stage</location>
        <length>20</length>
        <eventnumber>8141</eventnumber>
        <date>
          <eventdate>2018/11/15</eventdate>
          <times>
            <time>
              <starttime schoolonly="0">15:30</starttime>
              <endtime schoolonly="0">15:50</endtime>
              <instock>30000</instock>
            </time>
          </times>
        </date>
      </show>
      <show>
        <title>Science Snapshot</title>
        <location>Gordon Current Science &amp; Technology Center</location>
        <length>20</length>
        <eventnumber>8142</eventnumber>
        <date>
          <eventdate>2018/11/15</eventdate>
          <times>
            <time>
              <starttime schoolonly="0">12:30</starttime>
              <endtime schoolonly="0">12:50</endtime>
              <instock>30000</instock>
            </time>
          </times>
        </date>
      </show>
      <show>
        <title>Supercold Science</title>
        <location>Shapiro Family Science Live! Stage</location>
        <length>20</length>
        <eventnumber>6080</eventnumber>
        <date>
          <eventdate>2018/11/15</eventdate>
          <times>
            <time>
              <starttime schoolonly="0">11:30</starttime>
              <endtime schoolonly="0">11:50</endtime>
              <instock>30000</instock>
            </time>
          </times>
        </date>
      </show>
      <show>
        <title>What's Up in Space?</title>
        <location>Gordon Current Science &amp; Technology Center</location>
        <length>20</length>
        <eventnumber>46029</eventnumber>
        <date>
          <eventdate>2018/11/15</eventdate>
          <times>
            <time>
              <starttime schoolonly="0">11:00</starttime>
              <endtime schoolonly="0">11:20</endtime>
              <instock>30000</instock>
            </time>
          </times>
        </date>
      </show>
    </shows>
  </venue>
  <venue>
    <title>Mugar Omni Theater</title>
    <memberonly>0</memberonly>
    <capacity>314</capacity>
    <shows>
      <show>
        <title>Great Barrier Reef</title>
        <location>Mugar Omni Theater</location>
        <length>50</length>
        <eventnumber>41497</eventnumber>
        <date>
          <eventdate>2018/11/15</eventdate>
          <times>
            <time>
              <starttime schoolonly="0">12:00</starttime>
              <endtime schoolonly="0">12:50</endtime>
              <instock>302</instock>
            </time>
            <time>
              <starttime schoolonly="0">15:00</starttime>
              <endtime schoolonly="0">15:50</endtime>
              <instock>310</instock>
            </time>
          </times>
        </date>
      </show>
      <show>
        <title>Lewis &amp; Clark (For Schools Only)</title>
        <location>Mugar Omni Theater</location>
        <length>50</length>
        <eventnumber>1209</eventnumber>
        <date>
          <eventdate>2018/11/15</eventdate>
          <times>
            <time>
              <starttime schoolonly="1">11:00</starttime>
              <endtime schoolonly="1">11:50</endtime>
              <instock>100</instock>
            </time>
          </times>
        </date>
      </show>
      <show>
        <title>Pandas</title>
        <location>Mugar Omni Theater</location>
        <length>50</length>
        <eventnumber>43765</eventnumber>
        <date>
          <eventdate>2018/11/15</eventdate>
          <times>
            <time>
              <starttime schoolonly="0">14:00</starttime>
              <endtime schoolonly="0">14:50</endtime>
              <instock>282</instock>
            </time>
          </times>
        </date>
      </show>
      <show>
        <title>Volcanoes</title>
        <location>Mugar Omni Theater</location>
        <length>50</length>
        <eventnumber>48713</eventnumber>
        <date>
          <eventdate>2018/11/15</eventdate>
          <times>
            <time>
              <starttime schoolonly="0">10:00</starttime>
              <endtime schoolonly="0">10:50</endtime>
              <instock>296</instock>
            </time>
            <time>
              <starttime schoolonly="0">13:00</starttime>
              <endtime schoolonly="0">13:50</endtime>
              <instock>280</instock>
            </time>
            <time>
              <starttime schoolonly="0">16:00</starttime>
              <endtime schoolonly="0">16:50</endtime>
              <instock>299</instock>
            </time>
          </times>
        </date>
      </show>
    </shows>
  </venue>
  <venue>
    <title>Mugar Omni Theater</title>
    <memberonly>0</memberonly>
    <capacity>364</capacity>
    <shows>
      <show>
        <title>Pandas</title>
        <location>Mugar Omni Theater</location>
        <length>50</length>
        <eventnumber>43765</eventnumber>
        <date>
          <eventdate>2018/11/15</eventdate>
          <times>
            <time>
              <starttime schoolonly="0">17:00</starttime>
              <endtime schoolonly="0">17:50</endtime>
              <instock>308</instock>
            </time>
          </times>
        </date>
      </show>
    </shows>
  </venue>
  <venue>
    <title>School Lunch</title>
    <memberonly>0</memberonly>
    <capacity>200</capacity>
    <shows>
      <show>
        <title>School Lunch</title>
        <location>School Lunch</location>
        <length>25</length>
        <eventnumber>1149</eventnumber>
        <date>
          <eventdate>2018/11/15</eventdate>
          <times>
            <time>
              <starttime schoolonly="1">10:30</starttime>
              <endtime schoolonly="1">10:55</endtime>
              <instock>200</instock>
            </time>
            <time>
              <starttime schoolonly="1">11:00</starttime>
              <endtime schoolonly="1">11:25</endtime>
              <instock>200</instock>
            </time>
            <time>
              <starttime schoolonly="1">11:30</starttime>
              <endtime schoolonly="1">11:55</endtime>
              <instock>0</instock>
            </time>
            <time>
              <starttime schoolonly="1">12:00</starttime>
              <endtime schoolonly="1">12:25</endtime>
              <instock>0</instock>
            </time>
            <time>
              <starttime schoolonly="1">12:30</starttime>
              <endtime schoolonly="1">12:55</endtime>
              <instock>89</instock>
            </time>
            <time>
              <starttime schoolonly="1">13:00</starttime>
              <endtime schoolonly="1">13:25</endtime>
              <instock>130</instock>
            </time>
            <time>
              <starttime schoolonly="1">13:30</starttime>
              <endtime schoolonly="1">13:55</endtime>
              <instock>200</instock>
            </time>
            <time>
              <starttime schoolonly="1">14:00</starttime>
              <endtime schoolonly="1">14:25</endtime>
              <instock>200</instock>
            </time>
          </times>
        </date>
      </show>
    </shows>
  </venue>
</products>